ji_auth/__init__.py
ji_auth/__main__.py
ji_auth/canvas.py
ji_auth/coursesel.py
ji_auth/joj.py
ji_auth/login.py
ji_auth-0.0.8.dist-info/LICENSE
ji_auth-0.0.8.dist-info/METADATA
ji_auth-0.0.8.dist-info/WHEEL
ji_auth-0.0.8.dist-info/entry_points.txt
ji_auth-0.0.8.dist-info/top_level.txt
ji_auth-0.0.8.dist-info/RECORD
