Metadata-Version: 2.1
Name: ji-auth
Version: 0.0.8
Summary: Canvas token and JOJ SID are within reach in CLI.
Home-page: https://github.com/BoYanZh/JI-Auth
Author: BoYanZh
Author-email: bomingzh@sjtu.edu.cn
Maintainer: BoYanZh
Maintainer-email: bomingzh@sjtu.edu.cn
License: MIT
Requires-Python: >=3.6
License-File: LICENSE
Requires-Dist: aiohttp
Requires-Dist: beautifulsoup4
Requires-Dist: jaccount-auth
Requires-Dist: typer
